labyr/__init__.py
labyr/__main__.py
labyr/_secret.py
labyr/utils/__init__.py
labyr/utils/color.py
labyr/utils/dot.py
labyr/utils/entity.py
labyr/utils/fill.py
labyr/utils/transform.py
labyr-0.8.4.dist-info/licenses/LICENSE
labyr-0.8.4.dist-info/METADATA
labyr-0.8.4.dist-info/WHEEL
labyr-0.8.4.dist-info/entry_points.txt
labyr-0.8.4.dist-info/top_level.txt
labyr-0.8.4.dist-info/RECORD
