Metadata-Version: 2.4
Name: labyr
Version: 0.8.4
Summary: A labyrinth game.
Author-email: sigmacodeslol <tcrrxzz@gmail.com>
License-Expression: MIT
Project-URL: Repository, https://github.com/sigmacodeslol/labyr.git
Classifier: Development Status :: 4 - Beta
Classifier: Programming Language :: Python :: 3.9
Classifier: Programming Language :: Python :: 3.10
Classifier: Programming Language :: Python :: 3.11
Classifier: Programming Language :: Python :: 3.12
Requires-Python: >=3.9
License-File: LICENSE
Requires-Dist: colorama
Dynamic: license-file
